Workbook

Sheet Revise esta hoja
B2: Ejercicio 2
B3: Resumen de 5 números
C4: =moras[[#Headers],[SALARIO]] -> SALARIO | D4: =moras[[#Headers],[EDAD]] -> EDAD
B5: Mínimo | C5: =MIN('Y esta otra'!C2:C5001) -> 0 | D5: =MIN('Y esta otra'!I2:I5001) -> 14
B6: Máximo | C6: =MAX('Y esta otra'!C2:C5001) -> 16858742 | D6: =MAX('Y esta otra'!I2:I5001) -> 99
B7: Primer Cuartil | C7: =_xlfn.PERCENTILE.INC('Revise esta hoja'!C4817:C5001, 0.25) -> #NUM! | D7: =_xlfn.PERCENTILE.INC('Y esta otra'!I2:I5001, 0.25) -> 31
B8: Mediana | C8: =MEDIAN('Y esta otra'!C2:C5001) -> 408100 | D8: =MEDIAN('Y esta otra'!I2:I5001) -> 40
B9: Tercer Cuartil | C9: =_xlfn.PERCENTILE.INC('Revise esta hoja'!C4819:C5003, 0.75) -> #NUM! | D9: =_xlfn.PERCENTILE.INC('Y esta otra'!I2:I5001, 0.75) -> 52
B10: Promedio | C10: =AVERAGE('Y esta otra'!C2:C5001) -> 657425.24 | D10: =AVERAGE('Y esta otra'!I2:I5001) -> 41.906344
B11: Para el siguiente ejercicio usamos
B12: Desviación estándar | C12: =_xlfn.STDEV.S(moras[SALARIO]) -> 811054.2 | D12: =moras[EDAD] -> 30

Sheet Y esta otra
A1: IDENTIFICACION | B1: SEXO | C1: SALARIO | D1: TIPO_ASEGURAMIENTO | E1: SECTOR | F1: INDICADOR_ACTIVO | G1: INDICADOR.EXTRANJERO | H1: INDICADOR_MOROSO | I1: EDAD | J1: Z-SCORE_SALARIO | K1: Z-SCORE_EDAD | L1: SALARIO-IMPUTADO | M1: TIPO_ASEGURADO_IMPUTADO | N1: EDAD_IMPUTADO
A2: 1 | B2: HOMBRE | D2: ASALARIADO | E2: SECTOR PUBLICO | F2: SI | G2: NO | H2: NO | I2: 42 | J2: =IF(1.96<ABS(C2-$S$23)/$S$24,"Atípico","No") -> No | K2: =IF(1.96<ABS((I2-$T$23)/$T$24),"Atípico", "No") -> No | L2: =IF(ISBLANK(C2),$S$23,C2) -> 657425.24 | M2: =IF(ISBLANK(D2),_xlfn.MODE.SNGL(moras[TIPO_ASEGURAMIENTO]),D2) -> ASALARIADO | N2: =IF(ISBLANK(moras[[#This Row],[EDAD]]),T23,moras[[#This Row],[EDAD]]) -> 42
A3: 2 | B3: HOMBRE | C3: 3315014 | D3: PENSIONADOS EN SU PROPIO SISTEMA | E3: SECTOR PUBLICO | F3: SI | G3: NO | H3: NO | I3: 77 | J3: =IF(1.96<ABS(C3-$S$23)/$S$24,"Atípico","No") -> Atípico | K3: =IF(1.96<ABS((I3-$T$23)/$T$24),"Atípico", "No") -> No | L3: =IF(ISBLANK(C3),$S$23,C3) -> 3315014 | M3: =IF(ISBLANK(D3),_xlfn.MODE.SNGL(moras[TIPO_ASEGURAMIENTO]),D3) -> PENSIONADOS EN SU PROPIO SISTEMA | N3: =IF(ISBLANK(moras[[#This Row],[EDAD]]),T24,moras[[#This Row],[EDAD]]) -> 77
A4: 3 | B4: MUJER | C4: 270486.01 | D4: ASALARIADO | E4: SECTOR PRIVADO | F4: SI | G4: NO | H4: NO | I4: 45 | J4: =IF(1.96<ABS(C4-$S$23)/$S$24,"Atípico","No") -> No | K4: =IF(1.96<ABS((I4-$T$23)/$T$24),"Atípico", "No") -> No | L4: =IF(ISBLANK(C4),$S$23,C4) -> 270486.01 | M4: =IF(ISBLANK(D4),_xlfn.MODE.SNGL(moras[TIPO_ASEGURAMIENTO]),D4) -> ASALARIADO | N4: =IF(ISBLANK(moras[[#This Row],[EDAD]]),T25,moras[[#This Row],[EDAD]]) -> 45
A5: 4 | B5: MUJER | C5: =MIN('Y esta otra'!C2) -> 0 | D5: ASALARIADO | E5: SECTOR PRIVADO | F5: SI | G5: NO | H5: NO | I5: 49 | J5: =IF(1.96<ABS(C5-$S$23)/$S$24,"Atípico","No") -> No | K5: =IF(1.96<ABS((I5-$T$23)/$T$24),"Atípico", "No") -> No | L5: =IF(ISBLANK(C5),$S$23,C5) -> 0 | M5: =IF(ISBLANK(D5),_xlfn.MODE.SNGL(moras[TIPO_ASEGURAMIENTO]),D5) -> ASALARIADO | N5: =IF(ISBLANK(moras[[#This Row],[EDAD]]),T26,moras[[#This Row],[EDAD]]) -> 49
A6: 5 | B6: MUJER | C6: 210000 | D6: ASALARIADO | E6: SECTOR PRIVADO | F6: SI | G6: NO | H6: NO | I6: 42 | J6: =IF(1.96<ABS(C6-$S$23)/$S$24,"Atípico","No") -> No | K6: =IF(1.96<ABS((I6-$T$23)/$T$24),"Atípico", "No") -> No | L6: =IF(ISBLANK(C6),$S$23,C6) -> 210000 | M6: =IF(ISBLANK(D6),_xlfn.MODE.SNGL(moras[TIPO_ASEGURAMIENTO]),D6) -> ASALARIADO | N6: =IF(ISBLANK(moras[[#This Row],[EDAD]]),T27,moras[[#This Row],[EDAD]]) -> 42 | T6: =INDEX(moras[TIPO_ASEGURAMIENTO],MATCH(MAX(IF(moras[TIPO_ASEGURAMIENTO]<>"",COUNTIF(moras[TIPO_ASEGURAMIENTO],moras[TIPO_ASEGURAMIENTO]))),IF(moras[TIPO_ASEGURAMIENTO]<>"",COUNTIF(moras[TIPO_ASEGURAMIENTO],moras[TIPO_ASEGURAMIENTO])),0)) -> #N/A
A7: 6 | B7: HOMBRE | C7: 397150 | D7: ASALARIADO | E7: SECTOR PRIVADO | F7: SI | G7: NO | H7: NO | I7: 44 | J7: =IF(1.96<ABS(C7-$S$23)/$S$24,"Atípico","No") -> No | K7: =IF(1.96<ABS((I7-$T$23)/$T$24),"Atípico", "No") -> No | L7: =IF(ISBLANK(C7),$S$23,C7) -> 397150 | M7: =IF(ISBLANK(D7),_xlfn.MODE.SNGL(moras[TIPO_ASEGURAMIENTO]),D7) -> ASALARIADO | N7: =IF(ISBLANK(moras[[#This Row],[EDAD]]),T28,moras[[#This Row],[EDAD]]) -> 44 | T7: =INDEX(moras[TIPO_ASEGURAMIENTO],MATCH(MAX(IF(moras[TIPO_ASEGURAMIENTO]<>"",COUNTIF(moras[TIPO_ASEGURAMIENTO],moras[TIPO_ASEGURAMIENTO]))),IF(moras[TIPO_ASEGURAMIENTO]<>"",COUNTIF(moras[TIPO_ASEGURAMIENTO],moras[TIPO_ASEGURAMIENTO])),0)) -> #N/A
A8: 7 | B8: HOMBRE | C8: 854712 | D8: ASALARIADO | E8: SECTOR PRIVADO | F8: SI | G8: NO | H8: NO | I8: 38 | J8: =IF(1.96<ABS(C8-$S$23)/$S$24,"Atípico","No") -> No | K8: =IF(1.96<ABS((I8-$T$23)/$T$24),"Atípico", "No") -> No | L8: =IF(ISBLANK(C8),$S$23,C8) -> 854712 | M8: =IF(ISBLANK(D8),_xlfn.MODE.SNGL(moras[TIPO_ASEGURAMIENTO]),D8) -> ASALARIADO | N8: =IF(ISBLANK(moras[[#This Row],[EDAD]]),T29,moras[[#This Row],[EDAD]]) -> 38 | R8: =INDEX(moras[TIPO_ASEGURAMIENTO],MATCH(MAX(IF(moras[TIPO_ASEGURAMIENTO]<>"",COUNTIF(moras[TIPO_ASEGURAMIENTO],moras[TIPO_ASEGURAMIENTO]))),IF(moras[TIPO_ASEGURAMIENTO]<>"",COUNTIF(moras[TIPO_ASEGURAMIENTO],moras[TIPO_ASEGURAMIENTO])),0)) -> #N/A
A9: 8 | B9: HOMBRE | C9: 401000 | D9: ASALARIADO | E9: SECTOR PRIVADO | F9: SI | G9: SI | H9: SI | I9: 36 | J9: =IF(1.96<ABS(C9-$S$23)/$S$24,"Atípico","No") -> No | K9: =IF(1.96<ABS((I9-$T$23)/$T$24),"Atípico", "No") -> No | L9: =IF(ISBLANK(C9),$S$23,C9) -> 401000 | M9: =IF(ISBLANK(D9),_xlfn.MODE.SNGL(moras[TIPO_ASEGURAMIENTO]),D9) -> ASALARIADO | N9: =IF(ISBLANK(moras[[#This Row],[EDAD]]),T30,moras[[#This Row],[EDAD]]) -> 36
A10: 9 | B10: MUJER | C10: 264703.96 | D10: ASALARIADO | E10: SECTOR PRIVADO | F10: SI | G10: NO | H10: NO | I10: 21 | J10: =IF(1.96<ABS(C10-$S$23)/$S$24,"Atípico","No") -> No | K10: =IF(1.96<ABS((I10-$T$23)/$T$24),"Atípico", "No") -> No | L10: =IF(ISBLANK(C10),$S$23,C10) -> 264703.96 | M10: =IF(ISBLANK(D10),_xlfn.MODE.SNGL(moras[TIPO_ASEGURAMIENTO]),D10) -> ASALARIADO | N10: =IF(ISBLANK(moras[[#This Row],[EDAD]]),T31,moras[[#This Row],[EDAD]]) -> 21
A11: 10 | B11: HOMBRE | C11: 4677126.8 | D11: ASALARIADO | E11: SECTOR PRIVADO | F11: SI | G11: NO | H11: NO | I11: 40 | J11: =IF(1.96<ABS(C11-$S$23)/$S$24,"Atípico","No") -> Atípico | K11: =IF(1.96<ABS((I11-$T$23)/$T$24),"Atípico", "No") -> No | L11: =IF(ISBLANK(C11),$S$23,C11) -> 4677126.8 | M11: =IF(ISBLANK(D11),_xlfn.MODE.SNGL(moras[TIPO_ASEGURAMIENTO]),D11) -> ASALARIADO | N11: =IF(ISBLANK(moras[[#This Row],[EDAD]]),T32,moras[[#This Row],[EDAD]]) -> 40
A12: 11 | B12: MUJER | C12: 1200000 | D12: ASALARIADO | E12: SECTOR PRIVADO | F12: SI | G12: NO | H12: NO | I12: 30 | J12: =IF(1.96<ABS(C12-$S$23)/$S$24,"Atípico","No") -> No | K12: =IF(1.96<ABS((I12-$T$23)/$T$24),"Atípico", "No") -> No | L12: =IF(ISBLANK(C12),$S$23,C12) -> 1200000 | M12: =IF(ISBLANK(D12),_xlfn.MODE.SNGL(moras[TIPO_ASEGURAMIENTO]),D12) -> ASALARIADO | N12: =IF(ISBLANK(moras[[#This Row],[EDAD]]),T33,moras[[#This Row],[EDAD]]) -> 30
A13: 12 | B13: MUJER | C13: 1030132 | D13: ASALARIADO | E13: SECTOR PUBLICO | F13: SI | G13: NO | H13: SI | I13: 58 | J13: =IF(1.96<ABS(C13-$S$23)/$S$24,"Atípico","No") -> No | K13: =IF(1.96<ABS((I13-$T$23)/$T$24),"Atípico", "No") -> No | L13: =IF(ISBLANK(C13),$S$23,C13) -> 1030132 | M13: =IF(ISBLANK(D13),_xlfn.MODE.SNGL(moras[TIPO_ASEGURAMIENTO]),D13) -> ASALARIADO | N13: =IF(ISBLANK(moras[[#This Row],[EDAD]]),T34,moras[[#This Row],[EDAD]]) -> 58 | T13: =INDEX(moras[TIPO_ASEGURAMIENTO],MATCH(MAX(IF(moras[TIPO_ASEGURAMIENTO]<>"",COUNTIF(moras[TIPO_ASEGURAMIENTO],moras[TIPO_ASEGURAMIENTO]))),IF(moras[TIPO_ASEGURAMIENTO]<>"",COUNTIF(moras[TIPO_ASEGURAMIENTO],moras[TIPO_ASEGURAMIENTO])),0)) -> #N/A
A14: 13 | B14: HOMBRE | C14: 731287.5 | D14: ASALARIADO | E14: SECTOR PUBLICO | F14: SI | G14: NO | H14: NO | I14: 40 | J14: =IF(1.96<ABS(C14-$S$23)/$S$24,"Atípico","No") -> No | K14: =IF(1.96<ABS((I14-$T$23)/$T$24),"Atípico", "No") -> No | L14: =IF(ISBLANK(C14),$S$23,C14) -> 731287.5 | M14: =IF(ISBLANK(D14),_xlfn.MODE.SNGL(moras[TIPO_ASEGURAMIENTO]),D14) -> ASALARIADO | N14: =IF(ISBLANK(moras[[#This Row],[EDAD]]),T35,moras[[#This Row],[EDAD]]) -> 40
A15: 14 | B15: HOMBRE | C15: 282305 | D15: ASEGURADO VOLUNTARIO | E15: SECTOR PRIVADO | F15: SI | G15: NO | H15: NO | I15: 51 | J15: =IF(1.96<ABS(C15-$S$23)/$S$24,"Atípico","No") -> No | K15: =IF(1.96<ABS((I15-$T$23)/$T$24),"Atípico", "No") -> No | L15: =IF(ISBLANK(C15),$S$23,C15) -> 282305 | M15: =IF(ISBLANK(D15),_xlfn.MODE.SNGL(moras[TIPO_ASEGURAMIENTO]),D15) -> ASEGURADO VOLUNTARIO | N15: =IF(ISBLANK(moras[[#This Row],[EDAD]]),T36,moras[[#This Row],[EDAD]]) -> 51 | P15: =MO -> #NAME?
A16: 15 | B16: MUJER | C16: 343390.86 | D16: TRABAJADOR INDEPENDIENTE | E16: SECTOR PRIVADO | F16: SI | G16: NO | H16: NO | I16: 59 | J16: =IF(1.96<ABS(C16-$S$23)/$S$24,"Atípico","No") -> No | K16: =IF(1.96<ABS((I16-$T$23)/$T$24),"Atípico", "No") -> No | L16: =IF(ISBLANK(C16),$S$23,C16) -> 343390.86 | M16: =IF(ISBLANK(D16),_xlfn.MODE.SNGL(moras[TIPO_ASEGURAMIENTO]),D16) -> TRABAJADOR INDEPENDIENTE | N16: =IF(ISBLANK(moras[[#This Row],[EDAD]]),T37,moras[[#This Row],[EDAD]]) -> 59
A17: 16 | B17: MUJER | C17: 1943489.5 | D17: ASALARIADO | E17: SECTOR PUBLICO | F17: SI | G17: NO | H17: NO | I17: 58 | J17: =IF(1.96<ABS(C17-$S$23)/$S$24,"Atípico","No") -> No | K17: =IF(1.96<ABS((I17-$T$23)/$T$24),"Atípico", "No") -> No | L17: =IF(ISBLANK(C17),$S$23,C17) -> 1943489.5 | M17: =IF(ISBLANK(D17),_xlfn.MODE.SNGL(moras[TIPO_ASEGURAMIENTO]),D17) -> ASALARIADO | N17: =IF(ISBLANK(moras[[#This Row],[EDAD]]),T38,moras[[#This Row],[EDAD]]) -> 58
A18: 17 | B18: MUJER | C18: 1108980 | D18: ASALARIADO | E18: SECTOR PUBLICO | F18: SI | G18: NO | H18: SI | I18: 36 | J18: =IF(1.96<ABS(C18-$S$23)/$S$24,"Atípico","No") -> No | K18: =IF(1.96<ABS((I18-$T$23)/$T$24),"Atípico", "No") -> No | L18: =IF(ISBLANK(C18),$S$23,C18) -> 1108980 | M18: =IF(ISBLANK(D18),_xlfn.MODE.SNGL(moras[TIPO_ASEGURAMIENTO]),D18) -> ASALARIADO | N18: =IF(ISBLANK(moras[[#This Row],[EDAD]]),T39,moras[[#This Row],[EDAD]]) -> 36
A19: 18 | B19: MUJER | C19: 133157 | D19: ASALARIADO | E19: SECTOR PRIVADO | F19: SI | G19: NO | H19: NO | I19: 39 | J19: =IF(1.96<ABS(C19-$S$23)/$S$24,"Atípico","No") -> No | K19: =IF(1.96<ABS((I19-$T$23)/$T$24),"Atípico", "No") -> No | L19: =IF(ISBLANK(C19),$S$23,C19) -> 133157 | M19: =IF(ISBLANK(D19),_xlfn.MODE.SNGL(moras[TIPO_ASEGURAMIENTO]),D19) -> ASALARIADO | N19: =IF(ISBLANK(moras[[#This Row],[EDAD]]),T40,moras[[#This Row],[EDAD]]) -> 39
A20: 19 | B20: HOMBRE | C20: 553939 | D20: ASALARIADO | E20: SECTOR PRIVADO | F20: SI | G20: NO | H20: NO | I20: 45 | J20: =IF(1.96<ABS(C20-$S$23)/$S$24,"Atípico","No") -> No | K20: =IF(1.96<ABS((I20-$T$23)/$T$24),"Atípico", "No") -> No | L20: =IF(ISBLANK(C20),$S$23,C20) -> 553939 | M20: =IF(ISBLANK(D20),_xlfn.MODE.SNGL(moras[TIPO_ASEGURAMIENTO]),D20) -> ASALARIADO | N20: =IF(ISBLANK(moras[[#This Row],[EDAD]]),T41,moras[[#This Row],[EDAD]]) -> 45
A21: 20 | B21: MUJER | C21: 309820 | D21: ASEGURADO VOLUNTARIO | E21: SECTOR PRIVADO | F21: SI | G21: SI | H21: SI | I21: 52 | J21: =IF(1.96<ABS(C21-$S$23)/$S$24,"Atípico","No") -> No | K21: =IF(1.96<ABS((I21-$T$23)/$T$24),"Atípico", "No") -> No | L21: =IF(ISBLANK(C21),$S$23,C21) -> 309820 | M21: =IF(ISBLANK(D21),_xlfn.MODE.SNGL(moras[TIPO_ASEGURAMIENTO]),D21) -> ASEGURADO VOLUNTARIO | N21: =IF(ISBLANK(moras[[#This Row],[EDAD]]),T42,moras[[#This Row],[EDAD]]) -> 52
A22: 21 | B22: MUJER | D22: ASALARIADO | E22: SECTOR PRIVADO | F22: SI | G22: SI | H22: NO | I22: 28 | J22: =IF(1.96<ABS(C22-$S$23)/$S$24,"Atípico","No") -> No | K22: =IF(1.96<ABS((I22-$T$23)/$T$24),"Atípico", "No") -> No | L22: =IF(ISBLANK(C22),$S$23,C22) -> 657425.24 | M22: =IF(ISBLANK(D22),_xlfn.MODE.SNGL(moras[TIPO_ASEGURAMIENTO]),D22) -> ASALARIADO | N22: =IF(ISBLANK(moras[[#This Row],[EDAD]]),T43,moras[[#This Row],[EDAD]]) -> 28 | S22: salario | T22: edad
A23: 22 | B23: HOMBRE | C23: 278030 | D23: CONVENIOS ESPECIALES DE TRABAJADORES INDEPENDIENTES | E23: SECTOR PRIVADO | F23: SI | G23: NO | H23: NO | I23: 59 | J23: =IF(1.96<ABS(C23-$S$23)/$S$24,"Atípico","No") -> No | K23: =IF(1.96<ABS((I23-$T$23)/$T$24),"Atípico", "No") -> No | L23: =IF(ISBLANK(C23),$S$23,C23) -> 278030 | M23: =IF(ISBLANK(D23),_xlfn.MODE.SNGL(moras[TIPO_ASEGURAMIENTO]),D23) -> CONVENIOS ESPECIALES DE TRABAJADORES INDEPENDIENTES | N23: =IF(ISBLANK(moras[[#This Row],[EDAD]]),T44,moras[[#This Row],[EDAD]]) -> 59 | R23: Promedio | S23: ='Revise esta hoja'!C10 -> 657425.24 | T23: ='Revise esta hoja'!D10 -> 41.906344
A24: 23 | B24: HOMBRE | C24: 2124814 | D24: ASALARIADO | E24: SECTOR PRIVADO | F24: SI | G24: NO | H24: NO | I24: 32 | J24: =IF(1.96<ABS(C24-$S$23)/$S$24,"Atípico","No") -> No | K24: =IF(1.96<ABS((I24-$T$23)/$T$24),"Atípico", "No") -> No | L24: =IF(ISBLANK(C24),$S$23,C24) -> 2124814 | M24: =IF(ISBLANK(D24),_xlfn.MODE.SNGL(moras[TIPO_ASEGURAMIENTO]),D24) -> ASALARIADO | N24: =IF(ISBLANK(moras[[#This Row],[EDAD]]),T45,moras[[#This Row],[EDAD]]) -> 32 | R24: desviacion | S24: ='Revise esta hoja'!C12 -> 811054.2 | T24: ='Revise esta hoja'!D12 -> 30
A25: 24 | B25: HOMBRE | C25: 191744.68 | D25: ASALARIADO | E25: SECTOR PRIVADO | F25: SI | G25: NO | H25: NO | I25: 18 | J25: =IF(1.96<ABS(C25-$S$23)/$S$24,"Atípico","No") -> No | K25: =IF(1.96<ABS((I25-$T$23)/$T$24),"Atípico", "No") -> No | L25: =IF(ISBLANK(C25),$S$23,C25) -> 191744.68 | M25: =IF(ISBLANK(D25),_xlfn.MODE.SNGL(moras[TIPO_ASEGURAMIENTO]),D25) -> ASALARIADO | N25: =IF(ISBLANK(moras[[#This Row],[EDAD]]),T46,moras[[#This Row],[EDAD]]) -> 18
A26: 25 | B26: MUJER | C26: 1117489 | D26: ASALARIADO | E26: SECTOR PUBLICO | F26: SI | G26: NO | H26: SI | I26: 36 | J26: =IF(1.96<ABS(C26-$S$23)/$S$24,"Atípico","No") -> No | K26: =IF(1.96<ABS((I26-$T$23)/$T$24),"Atípico", "No") -> No | L26: =IF(ISBLANK(C26),$S$23,C26) -> 1117489 | M26: =IF(ISBLANK(D26),_xlfn.MODE.SNGL(moras[TIPO_ASEGURAMIENTO]),D26) -> ASALARIADO | N26: =IF(ISBLANK(moras[[#This Row],[EDAD]]),T47,moras[[#This Row],[EDAD]]) -> 36 | Q26: Valores faltantes | R26: Cantidad | S26: Porcentaje | U26: Cantiddad de filas
A27: 26 | B27: HOMBRE | C27: 1451530 | D27: PENSIONADOS EN SU PROPIO SISTEMA | E27: SECTOR PUBLICO | F27: SI | G27: NO | H27: NO | I27: 62 | J27: =IF(1.96<ABS(C27-$S$23)/$S$24,"Atípico","No") -> No | K27: =IF(1.96<ABS((I27-$T$23)/$T$24),"Atípico", "No") -> No | L27: =IF(ISBLANK(C27),$S$23,C27) -> 1451530 | M27: =IF(ISBLANK(D27),_xlfn.MODE.SNGL(moras[TIPO_ASEGURAMIENTO]),D27) -> PENSIONADOS EN SU PROPIO SISTEMA | N27: =IF(ISBLANK(moras[[#This Row],[EDAD]]),T48,moras[[#This Row],[EDAD]]) -> 62 | Q27: =moras[[#Headers],[IDENTIFICACION]] -> IDENTIFICACION | R27: =COUNTBLANK(moras[[#Headers],[IDENTIFICACION]]) -> 0 | S27: =R27/$U$27 -> 0 | U27: =COUNT(moras[IDENTIFICACION]) -> 5000
A28: 27 | B28: HOMBRE | C28: 66700 | D28: ASALARIADO | E28: SECTOR PRIVADO | F28: SI | G28: NO | H28: NO | I28: 38 | J28: =IF(1.96<ABS(C28-$S$23)/$S$24,"Atípico","No") -> No | K28: =IF(1.96<ABS((I28-$T$23)/$T$24),"Atípico", "No") -> No | L28: =IF(ISBLANK(C28),$S$23,C28) -> 66700 | M28: =IF(ISBLANK(D28),_xlfn.MODE.SNGL(moras[TIPO_ASEGURAMIENTO]),D28) -> ASALARIADO | N28: =IF(ISBLANK(moras[[#This Row],[EDAD]]),T49,moras[[#This Row],[EDAD]]) -> 38 | Q28: =moras[[#Headers],[SEXO]] -> SEXO | R28: =COUNTBLANK(B2:B5001) -> 0 | S28: =R28/$U$27 -> 0
A29: 28 | B29: MUJER | C29: 73410 | D29: ASALARIADO | E29: SECTOR PRIVADO | F29: SI | G29: SI | H29: NO | I29: 22 | J29: =IF(1.96<ABS(C29-$S$23)/$S$24,"Atípico","No") -> No | K29: =IF(1.96<ABS((I29-$T$23)/$T$24),"Atípico", "No") -> No | L29: =IF(ISBLANK(C29),$S$23,C29) -> 73410 | M29: =IF(ISBLANK(D29),_xlfn.MODE.SNGL(moras[TIPO_ASEGURAMIENTO]),D29) -> ASALARIADO | N29: =IF(ISBLANK(moras[[#This Row],[EDAD]]),T50,moras[[#This Row],[EDAD]]) -> 22 | Q29: =moras[[#Headers],[SALARIO]] -> SALARIO | R29: =COUNTBLANK(moras[SALARIO]) -> 3 | S29: =R29/$U$27 -> 0.0006
A30: 29 | B30: HOMBRE | C30: 815355.66 | D30: ASALARIADO | E30: SECTOR PUBLICO | F30: SI | G30: NO | H30: NO | I30: 42 | J30: =IF(1.96<ABS(C30-$S$23)/$S$24,"Atípico","No") -> No | K30: =IF(1.96<ABS((I30-$T$23)/$T$24),"Atípico", "No") -> No | L30: =IF(ISBLANK(C30),$S$23,C30) -> 815355.66 | M30: =IF(ISBLANK(D30),_xlfn.MODE.SNGL(moras[TIPO_ASEGURAMIENTO]),D30) -> ASALARIADO | N30: =IF(ISBLANK(moras[[#This Row],[EDAD]]),T51,moras[[#This Row],[EDAD]]) -> 42 | Q30: =moras[[#Headers],[TIPO_ASEGURAMIENTO]] -> TIPO_ASEGURAMIENTO | R30: =COUNTBLANK(moras[TIPO_ASEGURAMIENTO]) -> 2 | S30: =R30/$U$27 -> 0.0004
A31: 30 | B31: HOMBRE | C31: 398125 | D31: ASALARIADO | E31: SECTOR PRIVADO | F31: SI | G31: NO | H31: NO | I31: 38 | J31: =IF(1.96<ABS(C31-$S$23)/$S$24,"Atípico","No") -> No | K31: =IF(1.96<ABS((I31-$T$23)/$T$24),"Atípico", "No") -> No | L31: =IF(ISBLANK(C31),$S$23,C31) -> 398125 | M31: =IF(ISBLANK(D31),_xlfn.MODE.SNGL(moras[TIPO_ASEGURAMIENTO]),D31) -> ASALARIADO | N31: =IF(ISBLANK(moras[[#This Row],[EDAD]]),T52,moras[[#This Row],[EDAD]]) -> 38 | Q31: =moras[[#Headers],[SECTOR]] -> SECTOR | R31: =COUNTBLANK(moras[SECTOR]) -> 0 | S31: =R31/$U$27 -> 0 | W31: =INDEX(moras[TIPO_ASEGURAMIENTO],_xlfn.MODE.SNGL(IF(moras[TIPO_ASEGURAMIENTO]<>"", MATCH(moras[TIPO_ASEGURAMIENTO], moras[TIPO_ASEGURAMIENTO],0)))) -> #N/A
A32: 31 | B32: HOMBRE | C32: 606763.96 | D32: ASALARIADO | E32: SECTOR PRIVADO | F32: SI | G32: NO | H32: NO | I32: 39 | J32: =IF(1.96<ABS(C32-$S$23)/$S$24,"Atípico","No") -> No | K32: =IF(1.96<ABS((I32-$T$23)/$T$24),"Atípico", "No") -> No | L32: =IF(ISBLANK(C32),$S$23,C32) -> 606763.96 | M32: =IF(ISBLANK(D32),_xlfn.MODE.SNGL(moras[TIPO_ASEGURAMIENTO]),D32) -> ASALARIADO | N32: =IF(ISBLANK(moras[[#This Row],[EDAD]]),T53,moras[[#This Row],[EDAD]]) -> 39 | Q32: =moras[[#Headers],[INDICADOR_ACTIVO]] -> INDICADOR_ACTIVO | R32: =COUNTBLANK(moras[INDICADOR_ACTIVO]) -> 0 | S32: =R32/$U$27 -> 0
A33: 32 | B33: HOMBRE | C33: 360420 | D33: TRABAJADOR INDEPENDIENTE | E33: SECTOR PRIVADO | F33: SI | G33: NO | H33: SI | I33: 53 | J33: =IF(1.96<ABS(C33-$S$23)/$S$24,"Atípico","No") -> No | K33: =IF(1.96<ABS((I33-$T$23)/$T$24),"Atípico", "No") -> No | L33: =IF(ISBLANK(C33),$S$23,C33) -> 360420 | M33: =IF(ISBLANK(D33),_xlfn.MODE.SNGL(moras[TIPO_ASEGURAMIENTO]),D33) -> TRABAJADOR INDEPENDIENTE | N33: =IF(ISBLANK(moras[[#This Row],[EDAD]]),T54,moras[[#This Row],[EDAD]]) -> 53 | Q33: =moras[[#Headers],[INDICADOR.EXTRANJERO]] -> INDICADOR.EXTRANJERO | R33: =COUNTBLANK(moras[INDICADOR.EXTRANJERO]) -> 0 | S33: =R33/$U$27 -> 0
A34: 33 | B34: MUJER | C34: 297046 | D34: ASALARIADO | E34: SECTOR PRIVADO | F34: SI | G34: SI | H34: NO | I34: 41 | J34: =IF(1.96<ABS(C34-$S$23)/$S$24,"Atípico","No") -> No | K34: =IF(1.96<ABS((I34-$T$23)/$T$24),"Atípico", "No") -> No | L34: =IF(ISBLANK(C34),$S$23,C34) -> 297046 | M34: =IF(ISBLANK(D34),_xlfn.MODE.SNGL(moras[TIPO_ASEGURAMIENTO]),D34) -> ASALARIADO | N34: =IF(ISBLANK(moras[[#This Row],[EDAD]]),T55,moras[[#This Row],[EDAD]]) -> 41 | Q34: =moras[[#Headers],[INDICADOR_MOROSO]] -> INDICADOR_MOROSO | R34: =COUNTBLANK(moras[INDICADOR_MOROSO]) -> 0 | S34: =R34/$U$27 -> 0
A35: 34 | B35: HOMBRE | C35: 558030 | D35: ASALARIADO | E35: SECTOR PRIVADO | F35: SI | G35: NO | H35: NO | I35: 28 | J35: =IF(1.96<ABS(C35-$S$23)/$S$24,"Atípico","No") -> No | K35: =IF(1.96<ABS((I35-$T$23)/$T$24),"Atípico", "No") -> No | L35: =IF(ISBLANK(C35),$S$23,C35) -> 558030 | M35: =IF(ISBLANK(D35),_xlfn.MODE.SNGL(moras[TIPO_ASEGURAMIENTO]),D35) -> ASALARIADO | N35: =IF(ISBLANK(moras[[#This Row],[EDAD]]),T56,moras[[#This Row],[EDAD]]) -> 28 | Q35: =moras[[#Headers],[EDAD]] -> EDAD | R35: =COUNTBLANK(moras[EDAD]) -> 3 | S35: =R35/$U$27 -> 0.0006
A36: 35 | B36: HOMBRE | C36: 68309.03 | D36: ASALARIADO | E36: SECTOR PRIVADO | F36: SI | G36: NO | H36: NO | I36: 43 | J36: =IF(1.96<ABS(C36-$S$23)/$S$24,"Atípico","No") -> No | K36: =IF(1.96<ABS((I36-$T$23)/$T$24),"Atípico", "No") -> No | L36: =IF(ISBLANK(C36),$S$23,C36) -> 68309.03 | M36: =IF(ISBLANK(D36),_xlfn.MODE.SNGL(moras[TIPO_ASEGURAMIENTO]),D36) -> ASALARIADO | N36: =IF(ISBLANK(moras[[#This Row],[EDAD]]),T57,moras[[#This Row],[EDAD]]) -> 43
A37: 36 | B37: HOMBRE | D37: ASALARIADO | E37: SECTOR PUBLICO | F37: SI | G37: NO | H37: NO | I37: 62 | J37: =IF(1.96<ABS(C37-$S$23)/$S$24,"Atípico","No") -> No | K37: =IF(1.96<ABS((I37-$T$23)/$T$24),"Atípico", "No") -> No | L37: =IF(ISBLANK(C37),$S$23,C37) -> 657425.24 | M37: =IF(ISBLANK(D37),_xlfn.MODE.SNGL(moras[TIPO_ASEGURAMIENTO]),D37) -> ASALARIADO | N37: =IF(ISBLANK(moras[[#This Row],[EDAD]]),T58,moras[[#This Row],[EDAD]]) -> 62 | Q37: =moras[[#Headers],[SALARIO-IMPUTADO]] -> SALARIO-IMPUTADO | R37: =COUNTBLANK(moras[SALARIO-IMPUTADO]) -> 0
A38: 37 | B38: HOMBRE | C38: 1552307.5 | D38: ASALARIADO | E38: SECTOR PRIVADO | F38: SI | G38: SI | H38: NO | I38: 41 | J38: =IF(1.96<ABS(C38-$S$23)/$S$24,"Atípico","No") -> No | K38: =IF(1.96<ABS((I38-$T$23)/$T$24),"Atípico", "No") -> No | L38: =IF(ISBLANK(C38),$S$23,C38) -> 1552307.5 | M38: =IF(ISBLANK(D38),_xlfn.MODE.SNGL(moras[TIPO_ASEGURAMIENTO]),D38) -> ASALARIADO | N38: =IF(ISBLANK(moras[[#This Row],[EDAD]]),T59,moras[[#This Row],[EDAD]]) -> 41 | Q38: =moras[[#Headers],[TIPO_ASEGURADO_IMPUTADO]] -> TIPO_ASEGURADO_IMPUTADO | R38: =COUNTBLANK(moras[TIPO_ASEGURADO_IMPUTADO]) -> 0
A39: 38 | B39: HOMBRE | C39: 1531575 | D39: ASEGURADO VOLUNTARIO | E39: SECTOR PRIVADO | F39: SI | G39: SI | H39: NO | I39: 66 | J39: =IF(1.96<ABS(C39-$S$23)/$S$24,"Atípico","No") -> No | K39: =IF(1.96<ABS((I39-$T$23)/$T$24),"Atípico", "No") -> No | L39: =IF(ISBLANK(C39),$S$23,C39) -> 1531575 | M39: =IF(ISBLANK(D39),_xlfn.MODE.SNGL(moras[TIPO_ASEGURAMIENTO]),D39) -> ASEGURADO VOLUNTARIO | N39: =IF(ISBLANK(moras[[#This Row],[EDAD]]),T60,moras[[#This Row],[EDAD]]) -> 66 | Q39: =moras[[#Headers],[EDAD_IMPUTADO]] -> EDAD_IMPUTADO | R39: =COUNTBLANK(moras[EDAD_IMPUTADO]) -> 0
A40: 39 | B40: HOMBRE | C40: 3220569.1 | D40: ASALARIADO | E40: SECTOR PRIVADO | F40: SI | G40: NO | H40: NO | I40: 48 | J40: =IF(1.96<ABS(C40-$S$23)/$S$24,"Atípico","No") -> Atípico | K40: =IF(1.96<ABS((I40-$T$23)/$T$24),"Atípico", "No") -> No | L40: =IF(ISBLANK(C40),$S$23,C40) -> 3220569.1 | M40: =IF(ISBLANK(D40),_xlfn.MODE.SNGL(moras[TIPO_ASEGURAMIENTO]),D40) -> ASALARIADO | N40: =IF(ISBLANK(moras[[#This Row],[EDAD]]),T61,moras[[#This Row],[EDAD]]) -> 48 | Q40: Ahora vamos a imputar esos datos
A41: 40 | B41: HOMBRE | C41: 658917 | D41: ASALARIADO | E41: SECTOR PUBLICO | F41: SI | G41: NO | H41: SI | I41: 56 | J41: =IF(1.96<ABS(C41-$S$23)/$S$24,"Atípico","No") -> No | K41: =IF(1.96<ABS((I41-$T$23)/$T$24),"Atípico", "No") -> No | L41: =IF(ISBLANK(C41),$S$23,C41) -> 658917 | M41: =IF(ISBLANK(D41),_xlfn.MODE.SNGL(moras[TIPO_ASEGURAMIENTO]),D41) -> ASALARIADO | N41: =IF(ISBLANK(moras[[#This Row],[EDAD]]),T62,moras[[#This Row],[EDAD]]) -> 56
A42: 41 | B42: HOMBRE | C42: 631707.6 | D42: ASALARIADO | E42: SECTOR PRIVADO | F42: SI | G42: NO | H42: NO | I42: 25 | J42: =IF(1.96<ABS(C42-$S$23)/$S$24,"Atípico","No") -> No | K42: =IF(1.96<ABS((I42-$T$23)/$T$24),"Atípico", "No") -> No | L42: =IF(ISBLANK(C42),$S$23,C42) -> 631707.6 | M42: =IF(ISBLANK(D42),_xlfn.MODE.SNGL(moras[TIPO_ASEGURAMIENTO]),D42) -> ASALARIADO | N42: =IF(ISBLANK(moras[[#This Row],[EDAD]]),T63,moras[[#This Row],[EDAD]]) -> 25 | Q42: =IF(ISBLANK(C2),$S$23,C2) -> 657425.24
A43: 42 | B43: MUJER | C43: 977376 | D43: ASALARIADO | E43: SECTOR PRIVADO | F43: SI | G43: NO | H43: NO | I43: 33 | J43: =IF(1.96<ABS(C43-$S$23)/$S$24,"Atípico","No") -> No | K43: =IF(1.96<ABS((I43-$T$23)/$T$24),"Atípico", "No") -> No | L43: =IF(ISBLANK(C43),$S$23,C43) -> 977376 | M43: =IF(ISBLANK(D43),_xlfn.MODE.SNGL(moras[TIPO_ASEGURAMIENTO]),D43) -> ASALARIADO | N43: =IF(ISBLANK(moras[[#This Row],[EDAD]]),T64,moras[[#This Row],[EDAD]]) -> 33
A44: 43 | B44: MUJER | C44: 278030 | D44: CONVENIOS ESPECIALES DE TRABAJADORES INDEPENDIENTES | E44: SECTOR PRIVADO | F44: SI | G44: SI | H44: NO | I44: 23 | J44: =IF(1.96<ABS(C44-$S$23)/$S$24,"Atípico","No") -> No | K44: =IF(1.96<ABS((I44-$T$23)/$T$24),"Atípico", "No") -> No | L44: =IF(ISBLANK(C44),$S$23,C44) -> 278030 | M44: =IF(ISBLANK(D44),_xlfn.MODE.SNGL(moras[TIPO_ASEGURAMIENTO]),D44) -> CONVENIOS ESPECIALES DE TRABAJADORES INDEPENDIENTES | N44: =IF(ISBLANK(moras[[#This Row],[EDAD]]),T65,moras[[#This Row],[EDAD]]) -> 23 | U44: Gráficos del ejercicio 6
A45: 44 | B45: HOMBRE | C45: 633750 | D45: ASALARIADO | E45: SECTOR PRIVADO | F45: SI | G45: NO | H45: NO | I45: 43 | J45: =IF(1.96<ABS(C45-$S$23)/$S$24,"Atípico","No") -> No | K45: =IF(1.96<ABS((I45-$T$23)/$T$24),"Atípico", "No") -> No | L45: =IF(ISBLANK(C45),$S$23,C45) -> 633750 | M45: =IF(ISBLANK(D45),_xlfn.MODE.SNGL(moras[TIPO_ASEGURAMIENTO]),D45) -> ASALARIADO | N45: =IF(ISBLANK(moras[[#This Row],[EDAD]]),T66,moras[[#This Row],[EDAD]]) -> 43
A46: 45 | B46: MUJER | C46: 376776 | D46: ASALARIADO | E46: SECTOR PRIVADO | F46: SI | G46: NO | H46: NO | I46: 27 | J46: =IF(1.96<ABS(C46-$S$23)/$S$24,"Atípico","No") -> No | K46: =IF(1.96<ABS((I46-$T$23)/$T$24),"Atípico", "No") -> No | L46: =IF(ISBLANK(C46),$S$23,C46) -> 376776 | M46: =IF(ISBLANK(D46),_xlfn.MODE.SNGL(moras[TIPO_ASEGURAMIENTO]),D46) -> ASALARIADO | N46: =IF(ISBLANK(moras[[#This Row],[EDAD]]),T67,moras[[#This Row],[EDAD]]) -> 27
A47: 46 | B47: MUJER | C47: 1878386.2 | D47: ASALARIADO | E47: SECTOR PRIVADO | F47: SI | G47: NO | H47: NO | I47: 28 | J47: =IF(1.96<ABS(C47-$S$23)/$S$24,"Atípico","No") -> No | K47: =IF(1.96<ABS((I47-$T$23)/$T$24),"Atípico", "No") -> No | L47: =IF(ISBLANK(C47),$S$23,C47) -> 1878386.2 | M47: =IF(ISBLANK(D47),_xlfn.MODE.SNGL(moras[TIPO_ASEGURAMIENTO]),D47) -> ASALARIADO | N47: =IF(ISBLANK(moras[[#This Row],[EDAD]]),T68,moras[[#This Row],[EDAD]]) -> 28
A48: 47 | B48: MUJER | C48: 2224883 | D48: ASALARIADO | E48: SECTOR PRIVADO | F48: SI | G48: NO | H48: NO | I48: 49 | J48: =IF(1.96<ABS(C48-$S$23)/$S$24,"Atípico","No") -> No | K48: =IF(1.96<ABS((I48-$T$23)/$T$24),"Atípico", "No") -> No | L48: =IF(ISBLANK(C48),$S$23,C48) -> 2224883 | M48: =IF(ISBLANK(D48),_xlfn.MODE.SNGL(moras[TIPO_ASEGURAMIENTO]),D48) -> ASALARIADO | N48: =IF(ISBLANK(moras[[#This Row],[EDAD]]),T69,moras[[#This Row],[EDAD]]) -> 49
A49: 48 | B49: MUJER | C49: 349000 | D49: ASALARIADO | E49: SECTOR PRIVADO | F49: SI | G49: NO | H49: NO | I49: 36 | J49: =IF(1.96<ABS(C49-$S$23)/$S$24,"Atípico","No") -> No | K49: =IF(1.96<ABS((I49-$T$23)/$T$24),"Atípico", "No") -> No | L49: =IF(ISBLANK(C49),$S$23,C49) -> 349000 | M49: =IF(ISBLANK(D49),_xlfn.MODE.SNGL(moras[TIPO_ASEGURAMIENTO]),D49) -> ASALARIADO | N49: =IF(ISBLANK(moras[[#This Row],[EDAD]]),T70,moras[[#This Row],[EDAD]]) -> 36
A50: 49 | B50: HOMBRE | C50: 675069.69 | D50: ASALARIADO | E50: SECTOR PRIVADO | F50: SI | G50: NO | H50: NO | I50: 39 | J50: =IF(1.96<ABS(C50-$S$23)/$S$24,"Atípico","No") -> No | K50: =IF(1.96<ABS((I50-$T$23)/$T$24),"Atípico", "No") -> No | L50: =IF(ISBLANK(C50),$S$23,C50) -> 675069.69 | M50: =IF(ISBLANK(D50),_xlfn.MODE.SNGL(moras[TIPO_ASEGURAMIENTO]),D50) -> ASALARIADO | N50: =IF(ISBLANK(moras[[#This Row],[EDAD]]),T71,moras[[#This Row],[EDAD]]) -> 39
A51: 50 | B51: HOMBRE | C51: 443282 | D51: ASALARIADO | E51: SECTOR PRIVADO | F51: SI | G51: SI | H51: NO | J51: =IF(1.96<ABS(C51-$S$23)/$S$24,"Atípico","No") -> No | K51: =IF(1.96<ABS((I51-$T$23)/$T$24),"Atípico", "No") -> No | L51: =IF(ISBLANK(C51),$S$23,C51) -> 443282 | M51: =IF(ISBLANK(D51),_xlfn.MODE.SNGL(moras[TIPO_ASEGURAMIENTO]),D51) -> ASALARIADO | N51: =IF(ISBLANK(moras[[#This Row],[EDAD]]),T72,moras[[#This Row],[EDAD]]) -> 0
A52: 51 | B52: HOMBRE | C52: 297044.99 | D52: TRABAJADOR INDEPENDIENTE | E52: SECTOR PRIVADO | F52: SI | G52: NO | H52: NO | I52: 66 | J52: =IF(1.96<ABS(C52-$S$23)/$S$24,"Atípico","No") -> No | K52: =IF(1.96<ABS((I52-$T$23)/$T$24),"Atípico", "No") -> No | L52: =IF(ISBLANK(C52),$S$23,C52) -> 297044.99 | M52: =IF(ISBLANK(D52),_xlfn.MODE.SNGL(moras[TIPO_ASEGURAMIENTO]),D52) -> TRABAJADOR INDEPENDIENTE | N52: =IF(ISBLANK(moras[[#This Row],[EDAD]]),T73,moras[[#This Row],[EDAD]]) -> 66
A53: 52 | B53: HOMBRE | C53: 1505458.9 | D53: ASALARIADO | E53: SECTOR PUBLICO | F53: SI | G53: NO | H53: NO | J53: =IF(1.96<ABS(C53-$S$23)/$S$24,"Atípico","No") -> No | K53: =IF(1.96<ABS((I53-$T$23)/$T$24),"Atípico", "No") -> No | L53: =IF(ISBLANK(C53),$S$23,C53) -> 1505458.9 | M53: =IF(ISBLANK(D53),_xlfn.MODE.SNGL(moras[TIPO_ASEGURAMIENTO]),D53) -> ASALARIADO | N53: =IF(ISBLANK(moras[[#This Row],[EDAD]]),T74,moras[[#This Row],[EDAD]]) -> 0
A54: 53 | B54: MUJER | C54: 743436 | D54: ASALARIADO | E54: SECTOR PRIVADO | F54: SI | G54: NO | H54: NO | I54: 28 | J54: =IF(1.96<ABS(C54-$S$23)/$S$24,"Atípico","No") -> No | K54: =IF(1.96<ABS((I54-$T$23)/$T$24),"Atípico", "No") -> No | L54: =IF(ISBLANK(C54),$S$23,C54) -> 743436 | M54: =IF(ISBLANK(D54),_xlfn.MODE.SNGL(moras[TIPO_ASEGURAMIENTO]),D54) -> ASALARIADO | N54: =IF(ISBLANK(moras[[#This Row],[EDAD]]),T75,moras[[#This Row],[EDAD]]) -> 28
A55: 54 | B55: HOMBRE | C55: 379422 | D55: TRABAJADOR INDEPENDIENTE | E55: SECTOR PRIVADO | F55: SI | G55: NO | H55: NO | I55: 43 | J55: =IF(1.96<ABS(C55-$S$23)/$S$24,"Atípico","No") -> No | K55: =IF(1.96<ABS((I55-$T$23)/$T$24),"Atípico", "No") -> No | L55: =IF(ISBLANK(C55),$S$23,C55) -> 379422 | M55: =IF(ISBLANK(D55),_xlfn.MODE.SNGL(moras[TIPO_ASEGURAMIENTO]),D55) -> TRABAJADOR INDEPENDIENTE | N55: =IF(ISBLANK(moras[[#This Row],[EDAD]]),T76,moras[[#This Row],[EDAD]]) -> 43
A56: 55 | B56: HOMBRE | C56: 300000 | D56: ASEGURADO VOLUNTARIO | E56: SECTOR PRIVADO | F56: SI | G56: NO | H56: NO | I56: 44 | J56: =IF(1.96<ABS(C56-$S$23)/$S$24,"Atípico","No") -> No | K56: =IF(1.96<ABS((I56-$T$23)/$T$24),"Atípico", "No") -> No | L56: =IF(ISBLANK(C56),$S$23,C56) -> 300000 | M56: =IF(ISBLANK(D56),_xlfn.MODE.SNGL(moras[TIPO_ASEGURAMIENTO]),D56) -> ASEGURADO VOLUNTARIO | N56: =IF(ISBLANK(moras[[#This Row],[EDAD]]),T77,moras[[#This Row],[EDAD]]) -> 44
A57: 56 | B57: MUJER | C57: 159787.22 | D57: ASALARIADO | E57: SECTOR PRIVADO | F57: SI | G57: SI | H57: NO | I57: 44 | J57: =IF(1.96<ABS(C57-$S$23)/$S$24,"Atípico","No") -> No | K57: =IF(1.96<ABS((I57-$T$23)/$T$24),"Atípico", "No") -> No | L57: =IF(ISBLANK(C57),$S$23,C57) -> 159787.22 | M57: =IF(ISBLANK(D57),_xlfn.MODE.SNGL(moras[TIPO_ASEGURAMIENTO]),D57) -> ASALARIADO | N57: =IF(ISBLANK(moras[[#This Row],[EDAD]]),T78,moras[[#This Row],[EDAD]]) -> 44
A58: 57 | B58: MUJER | C58: 267741.04 | D58: ASALARIADO | E58: SECTOR PRIVADO | F58: SI | G58: NO | H58: NO | I58: 32 | J58: =IF(1.96<ABS(C58-$S$23)/$S$24,"Atípico","No") -> No | K58: =IF(1.96<ABS((I58-$T$23)/$T$24),"Atípico", "No") -> No | L58: =IF(ISBLANK(C58),$S$23,C58) -> 267741.04 | M58: =IF(ISBLANK(D58),_xlfn.MODE.SNGL(moras[TIPO_ASEGURAMIENTO]),D58) -> ASALARIADO | N58: =IF(ISBLANK(moras[[#This Row],[EDAD]]),T79,moras[[#This Row],[EDAD]]) -> 32
A59: 58 | B59: MUJER | C59: 376777 | D59: ASALARIADO | E59: SECTOR PRIVADO | F59: SI | G59: NO | H59: NO | I59: 43 | J59: =IF(1.96<ABS(C59-$S$23)/$S$24,"Atípico","No") -> No | K59: =IF(1.96<ABS((I59-$T$23)/$T$24),"Atípico", "No") -> No | L59: =IF(ISBLANK(C59),$S$23,C59) -> 376777 | M59: =IF(ISBLANK(D59),_xlfn.MODE.SNGL(moras[TIPO_ASEGURAMIENTO]),D59) -> ASALARIADO | N59: =IF(ISBLANK(moras[[#This Row],[EDAD]]),T80,moras[[#This Row],[EDAD]]) -> 43
A60: 59 | B60: HOMBRE | C60: 386161 | D60: TRABAJADOR INDEPENDIENTE | E60: SECTOR PRIVADO | F60: SI | G60: NO | H60: SI | I60: 45 | J60: =IF(1.96<ABS(C60-$S$23)/$S$24,"Atípico","No") -> No | K60: =IF(1.96<ABS((I60-$T$23)/$T$24),"Atípico", "No") -> No | L60: =IF(ISBLANK(C60),$S$23,C60) -> 386161 | M60: =IF(ISBLANK(D60),_xlfn.MODE.SNGL(moras[TIPO_ASEGURAMIENTO]),D60) -> TRABAJADOR INDEPENDIENTE | N60: =IF(ISBLANK(moras[[#This Row],[EDAD]]),T81,moras[[#This Row],[EDAD]]) -> 45
A61: 60 | B61: HOMBRE | C61: 278030 | D61: CONVENIOS ESPECIALES DE TRABAJADORES INDEPENDIENTES | E61: SECTOR PRIVADO | F61: SI | G61: NO | H61: NO | I61: 22 | J61: =IF(1.96<ABS(C61-$S$23)/$S$24,"Atípico","No") -> No | K61: =IF(1.96<ABS((I61-$T$23)/$T$24),"Atípico", "No") -> No | L61: =IF(ISBLANK(C61),$S$23,C61) -> 278030 | M61: =IF(ISBLANK(D61),_xlfn.MODE.SNGL(moras[TIPO_ASEGURAMIENTO]),D61) -> CONVENIOS ESPECIALES DE TRABAJADORES INDEPENDIENTES | N61: =IF(ISBLANK(moras[[#This Row],[EDAD]]),T82,moras[[#This Row],[EDAD]]) -> 22 | U61: En este gráfico podemos observar que hay una mayoría de hombres que de mujeres, donde los datos vienen de personas asalariadas, jubiladas, etc. Esto nos dice que hay más hombres que trabajan en esta población. | AB61: Para el salario imputado podemos ver que hay un promedio de salarios menores de dos millones y hay algunos outliers que llegan a un salario altísimo pero es un mismo bloque casi uniforme por unos pocos contados que ganan muy bien.
A62: 61 | B62: HOMBRE | C62: 1594012.7 | D62: ASALARIADO | E62: SECTOR PRIVADO | F62: SI | G62: NO | H62: NO | I62: 32 | J62: =IF(1.96<ABS(C62-$S$23)/$S$24,"Atípico","No") -> No | K62: =IF(1.96<ABS((I62-$T$23)/$T$24),"Atípico", "No") -> No | L62: =IF(ISBLANK(C62),$S$23,C62) -> 1594012.7 | M62: =IF(ISBLANK(D62),_xlfn.MODE.SNGL(moras[TIPO_ASEGURAMIENTO]),D62) -> ASALARIADO | N62: =IF(ISBLANK(moras[[#This Row],[EDAD]]),T83,moras[[#This Row],[EDAD]]) -> 32
A63: 62 | B63: HOMBRE | C63: 1401725 | D63: PENSIONADOS EN SU PROPIO SISTEMA | E63: SECTOR PUBLICO | F63: SI | G63: NO | H63: NO | I63: 85 | J63: =IF(1.96<ABS(C63-$S$23)/$S$24,"Atípico","No") -> No | K63: =IF(1.96<ABS((I63-$T$23)/$T$24),"Atípico", "No") -> No | L63: =IF(ISBLANK(C63),$S$23,C63) -> 1401725 | M63: =IF(ISBLANK(D63),_xlfn.MODE.SNGL(moras[TIPO_ASEGURAMIENTO]),D63) -> PENSIONADOS EN SU PROPIO SISTEMA | N63: =IF(ISBLANK(moras[[#This Row],[EDAD]]),T84,moras[[#This Row],[EDAD]]) -> 85
A64: 63 | B64: HOMBRE | C64: 366358.49 | D64: ASALARIADO | E64: SECTOR PRIVADO | F64: SI | G64: NO | H64: NO | I64: 51 | J64: =IF(1.96<ABS(C64-$S$23)/$S$24,"Atípico","No") -> No | K64: =IF(1.96<ABS((I64-$T$23)/$T$24),"Atípico", "No") -> No | L64: =IF(ISBLANK(C64),$S$23,C64) -> 366358.49 | M64: =IF(ISBLANK(D64),_xlfn.MODE.SNGL(moras[TIPO_ASEGURAMIENTO]),D64) -> ASALARIADO | N64: =IF(ISBLANK(moras[[#This Row],[EDAD]]),T85,moras[[#This Row],[EDAD]]) -> 51
A65: 64 | B65: MUJER | C65: 411794 | D65: TRABAJADOR INDEPENDIENTE | E65: SECTOR PRIVADO | F65: SI | G65: NO | H65: NO | I65: 53 | J65: =IF(1.96<ABS(C65-$S$23)/$S$24,"Atípico","No") -> No | K65: =IF(1.96<ABS((I65-$T$23)/$T$24),"Atípico", "No") -> No | L65: =IF(ISBLANK(C65),$S$23,C65) -> 411794 | M65: =IF(ISBLANK(D65),_xlfn.MODE.SNGL(moras[TIPO_ASEGURAMIENTO]),D65) -> TRABAJADOR INDEPENDIENTE | N65: =IF(ISBLANK(moras[[#This Row],[EDAD]]),T86,moras[[#This Row],[EDAD]]) -> 53
A66: 65 | B66: HOMBRE | C66: 340510.83 | D66: ASALARIADO | E66: SECTOR PRIVADO | F66: SI | G66: NO | H66: NO | I66: 40 | J66: =IF(1.96<ABS(C66-$S$23)/$S$24,"Atípico","No") -> No | K66: =IF(1.96<ABS((I66-$T$23)/$T$24),"Atípico", "No") -> No | L66: =IF(ISBLANK(C66),$S$23,C66) -> 340510.83 | M66: =IF(ISBLANK(D66),_xlfn.MODE.SNGL(moras[TIPO_ASEGURAMIENTO]),D66) -> ASALARIADO | N66: =IF(ISBLANK(moras[[#This Row],[EDAD]]),T87,moras[[#This Row],[EDAD]]) -> 40
A67: 66 | B67: HOMBRE | C67: 3217736 | D67: ASALARIADO | E67: SECTOR PRIVADO | F67: SI | G67: NO | H67: NO | I67: 32 | J67: =IF(1.96<ABS(C67-$S$23)/$S$24,"Atípico","No") -> Atípico | K67: =IF(1.96<ABS((I67-$T$23)/$T$24),"Atípico", "No") -> No | L67: =IF(ISBLANK(C67),$S$23,C67) -> 3217736 | M67: =IF(ISBLANK(D67),_xlfn.MODE.SNGL(moras[TIPO_ASEGURAMIENTO]),D67) -> ASALARIADO | N67: =IF(ISBLANK(moras[[#This Row],[EDAD]]),T88,moras[[#This Row],[EDAD]]) -> 32
A68: 67 | B68: HOMBRE | C68: 133603.53 | D68: PENSIONADOS EN SU PROPIO SISTEMA | E68: SECTOR PUBLICO | F68: SI | G68: NO | H68: NO | I68: 72 | J68: =IF(1.96<ABS(C68-$S$23)/$S$24,"Atípico","No") -> No | K68: =IF(1.96<ABS((I68-$T$23)/$T$24),"Atípico", "No") -> No | L68: =IF(ISBLANK(C68),$S$23,C68) -> 133603.53 | M68: =IF(ISBLANK(D68),_xlfn.MODE.SNGL(moras[TIPO_ASEGURAMIENTO]),D68) -> PENSIONADOS EN SU PROPIO SISTEMA | N68: =IF(ISBLANK(moras[[#This Row],[EDAD]]),T89,moras[[#This Row],[EDAD]]) -> 72
A69: 68 | B69: HOMBRE | C69: 140435.81 | D69: PENSIONADOS EN SU PROPIO SISTEMA | E69: SECTOR PUBLICO | F69: SI | G69: NO | H69: NO | I69: 74 | J69: =IF(1.96<ABS(C69-$S$23)/$S$24,"Atípico","No") -> No | K69: =IF(1.96<ABS((I69-$T$23)/$T$24),"Atípico", "No") -> No | L69: =IF(ISBLANK(C69),$S$23,C69) -> 140435.81 | M69: =IF(ISBLANK(D69),_xlfn.MODE.SNGL(moras[TIPO_ASEGURAMIENTO]),D69) -> PENSIONADOS EN SU PROPIO SISTEMA | N69: =IF(ISBLANK(moras[[#This Row],[EDAD]]),T90,moras[[#This Row],[EDAD]]) -> 74
A70: 69 | B70: HOMBRE | C70: 1866932.5 | D70: ASALARIADO | E70: SECTOR PUBLICO | F70: SI | G70: NO | H70: NO | I70: 57 | J70: =IF(1.96<ABS(C70-$S$23)/$S$24,"Atípico","No") -> No | K70: =IF(1.96<ABS((I70-$T$23)/$T$24),"Atípico", "No") -> No | L70: =IF(ISBLANK(C70),$S$23,C70) -> 1866932.5 | M70: =IF(ISBLANK(D70),_xlfn.MODE.SNGL(moras[TIPO_ASEGURAMIENTO]),D70) -> ASALARIADO | N70: =IF(ISBLANK(moras[[#This Row],[EDAD]]),T91,moras[[#This Row],[EDAD]]) -> 57
A71: 70 | B71: HOMBRE | C71: 299647 | D71: ASEGURADO VOLUNTARIO | E71: SECTOR PRIVADO | F71: SI | G71: NO | H71: NO | J71: =IF(1.96<ABS(C71-$S$23)/$S$24,"Atípico","No") -> No | K71: =IF(1.96<ABS((I71-$T$23)/$T$24),"Atípico", "No") -> No | L71: =IF(ISBLANK(C71),$S$23,C71) -> 299647 | M71: =IF(ISBLANK(D71),_xlfn.MODE.SNGL(moras[TIPO_ASEGURAMIENTO]),D71) -> ASEGURADO VOLUNTARIO | N71: =IF(ISBLANK(moras[[#This Row],[EDAD]]),T92,moras[[#This Row],[EDAD]]) -> 0
A72: 71 | B72: MUJER | C72: 544163.5 | D72: ASALARIADO | E72: SECTOR PRIVADO | F72: SI | G72: NO | H72: NO | I72: 24 | J72: =IF(1.96<ABS(C72-$S$23)/$S$24,"Atípico","No") -> No | K72: =IF(1.96<ABS((I72-$T$23)/$T$24),"Atípico", "No") -> No | L72: =IF(ISBLANK(C72),$S$23,C72) -> 544163.5 | M72: =IF(ISBLANK(D72),_xlfn.MODE.SNGL(moras[TIPO_ASEGURAMIENTO]),D72) -> ASALARIADO | N72: =IF(ISBLANK(moras[[#This Row],[EDAD]]),T93,moras[[#This Row],[EDAD]]) -> 24
A73: 72 | B73: MUJER | C73: 2128928 | E73: SECTOR PUBLICO | F73: SI | G73: NO | H73: SI | I73: 42 | J73: =IF(1.96<ABS(C73-$S$23)/$S$24,"Atípico","No") -> No | K73: =IF(1.96<ABS((I73-$T$23)/$T$24),"Atípico", "No") -> No | L73: =IF(ISBLANK(C73),$S$23,C73) -> 2128928 | M73: ASALARIADO | N73: =IF(ISBLANK(moras[[#This Row],[EDAD]]),T94,moras[[#This Row],[EDAD]]) -> 42
A74: 73 | B74: HOMBRE | C74: 278030 | D74: CONVENIOS ESPECIALES DE TRABAJADORES INDEPENDIENTES | E74: SECTOR PRIVADO | F74: SI | G74: NO | H74: NO | I74: 57 | J74: =IF(1.96<ABS(C74-$S$23)/$S$24,"Atípico","No") -> No | K74: =IF(1.96<ABS((I74-$T$23)/$T$24),"Atípico", "No") -> No | L74: =IF(ISBLANK(C74),$S$23,C74) -> 278030 | M74: =IF(ISBLANK(D74),_xlfn.MODE.SNGL(moras[TIPO_ASEGURAMIENTO]),D74) -> CONVENIOS ESPECIALES DE TRABAJADORES INDEPENDIENTES | N74: =IF(ISBLANK(moras[[#This Row],[EDAD]]),T95,moras[[#This Row],[EDAD]]) -> 57
A75: 74 | B75: MUJER | C75: 508972.8 | D75: ASALARIADO | E75: SECTOR PUBLICO | F75: SI | G75: NO | H75: NO | I75: 46 | J75: =IF(1.96<ABS(C75-$S$23)/$S$24,"Atípico","No") -> No | K75: =IF(1.96<ABS((I75-$T$23)/$T$24),"Atípico", "No") -> No | L75: =IF(ISBLANK(C75),$S$23,C75) -> 508972.8 | M75: =IF(ISBLANK(D75),_xlfn.MODE.SNGL(moras[TIPO_ASEGURAMIENTO]),D75) -> ASALARIADO | N75: =IF(ISBLANK(moras[[#This Row],[EDAD]]),T96,moras[[#This Row],[EDAD]]) -> 46
A76: 75 | B76: HOMBRE | C76: 476424.06 | D76: ASALARIADO | E76: SECTOR PRIVADO | F76: SI | G76: NO | H76: NO | I76: 24 | J76: =IF(1.96<ABS(C76-$S$23)/$S$24,"Atípico","No") -> No | K76: =IF(1.96<ABS((I76-$T$23)/$T$24),"Atípico", "No") -> No | L76: =IF(ISBLANK(C76),$S$23,C76) -> 476424.06 | M76: =IF(ISBLANK(D76),_xlfn.MODE.SNGL(moras[TIPO_ASEGURAMIENTO]),D76) -> ASALARIADO | N76: =IF(ISBLANK(moras[[#This Row],[EDAD]]),T97,moras[[#This Row],[EDAD]]) -> 24
A77: 76 | B77: MUJER | C77: 278035 | D77: TRABAJADOR INDEPENDIENTE | E77: SECTOR PRIVADO | F77: SI | G77: NO | H77: SI | I77: 27 | J77: =IF(1.96<ABS(C77-$S$23)/$S$24,"Atípico","No") -> No | K77: =IF(1.96<ABS((I77-$T$23)/$T$24),"Atípico", "No") -> No | L77: =IF(ISBLANK(C77),$S$23,C77) -> 278035 | M77: =IF(ISBLANK(D77),_xlfn.MODE.SNGL(moras[TIPO_ASEGURAMIENTO]),D77) -> TRABAJADOR INDEPENDIENTE | N77: =IF(ISBLANK(moras[[#This Row],[EDAD]]),T98,moras[[#This Row],[EDAD]]) -> 27
A78: 77 | B78: HOMBRE | C78: 297046 | D78: ASEGURADO VOLUNTARIO | E78: SECTOR PRIVADO | F78: NO | G78: NO | H78: SI | I78: 29 | J78: =IF(1.96<ABS(C78-$S$23)/$S$24,"Atípico","No") -> No | K78: =IF(1.96<ABS((I78-$T$23)/$T$24),"Atípico", "No") -> No | L78: =IF(ISBLANK(C78),$S$23,C78) -> 297046 | M78: =IF(ISBLANK(D78),_xlfn.MODE.SNGL(moras[TIPO_ASEGURAMIENTO]),D78) -> ASEGURADO VOLUNTARIO | N78: =IF(ISBLANK(moras[[#This Row],[EDAD]]),T99,moras[[#This Row],[EDAD]]) -> 29
A79: 78 | B79: MUJER | C79: 643859.2 | D79: ASALARIADO | E79: SECTOR PUBLICO | F79: SI | G79: NO | H79: NO | I79: 35 | J79: =IF(1.96<ABS(C79-$S$23)/$S$24,"Atípico","No") -> No | K79: =IF(1.96<ABS((I79-$T$23)/$T$24),"Atípico", "No") -> No | L79: =IF(ISBLANK(C79),$S$23,C79) -> 643859.2 | M79: =IF(ISBLANK(D79),_xlfn.MODE.SNGL(moras[TIPO_ASEGURAMIENTO]),D79) -> ASALARIADO | N79: =IF(ISBLANK(moras[[#This Row],[EDAD]]),T100,moras[[#This Row],[EDAD]]) -> 35
A80: 79 | B80: HOMBRE | C80: 364678.16 | D80: ASALARIADO | E80: SECTOR PRIVADO | F80: SI | G80: NO | H80: NO | I80: 28 | J80: =IF(1.96<ABS(C80-$S$23)/$S$24,"Atípico","No") -> No | K80: =IF(1.96<ABS((I80-$T$23)/$T$24),"Atípico", "No") -> No | L80: =IF(ISBLANK(C80),$S$23,C80) -> 364678.16 | M80: =IF(ISBLANK(D80),_xlfn.MODE.SNGL(moras[TIPO_ASEGURAMIENTO]),D80) -> ASALARIADO | N80: =IF(ISBLANK(moras[[#This Row],[EDAD]]),T101,moras[[#This Row],[EDAD]]) -> 28 | U80: Podemos ver que el tipo de asegurado más frecuente es el de los asalariados pero acá, a diferencia de otras variables, hay mucha variedad y los que tienen salario o trabajan en el momento tienen una frecuencia más alta a obtener el tipo de asegurado. | AB80: El sector privado tiene muchísima más frecuencia para obtener este tipo de bien y es cuatro veces más que el sector público lo que puede tener que ver con el salario de las personas del sector privado.
A81: 80 | B81: MUJER | C81: 297046 | D81: ASEGURADO VOLUNTARIO | E81: SECTOR PRIVADO | F81: SI | G81: NO | H81: NO | I81: 50 | J81: =IF(1.96<ABS(C81-$S$23)/$S$24,"Atípico","No") -> No | K81: =IF(1.96<ABS((I81-$T$23)/$T$24),"Atípico", "No") -> No | L81: =IF(ISBLANK(C81),$S$23,C81) -> 297046 | M81: =IF(ISBLANK(D81),_xlfn.MODE.SNGL(moras[TIPO_ASEGURAMIENTO]),D81) -> ASEGURADO VOLUNTARIO | N81: =IF(ISBLANK(moras[[#This Row],[EDAD]]),T102,moras[[#This Row],[EDAD]]) -> 50
A82: 81 | B82: MUJER | C82: 909000 | D82: ASALARIADO | E82: SECTOR PRIVADO | F82: SI | G82: NO | H82: SI | I82: 27 | J82: =IF(1.96<ABS(C82-$S$23)/$S$24,"Atípico","No") -> No | K82: =IF(1.96<ABS((I82-$T$23)/$T$24),"Atípico", "No") -> No | L82: =IF(ISBLANK(C82),$S$23,C82) -> 909000 | M82: =IF(ISBLANK(D82),_xlfn.MODE.SNGL(moras[TIPO_ASEGURAMIENTO]),D82) -> ASALARIADO | N82: =IF(ISBLANK(moras[[#This Row],[EDAD]]),T103,moras[[#This Row],[EDAD]]) -> 27
A83: 82 | B83: MUJER | C83: 1769611 | D83: ASALARIADO | E83: SECTOR PUBLICO | F83: SI | G83: NO | H83: NO | I83: 56 | J83: =IF(1.96<ABS(C83-$S$23)/$S$24,"Atípico","No") -> No | K83: =IF(1.96<ABS((I83-$T$23)/$T$24),"Atípico", "No") -> No | L83: =IF(ISBLANK(C83),$S$23,C83) -> 1769611 | M83: =IF(ISBLANK(D83),_xlfn.MODE.SNGL(moras[TIPO_ASEGURAMIENTO]),D83) -> ASALARIADO | N83: =IF(ISBLANK(moras[[#This Row],[EDAD]]),T104,moras[[#This Row],[EDAD]]) -> 56
A84: 83 | B84: HOMBRE | C84: 415861 | D84: TRABAJADOR INDEPENDIENTE | E84: SECTOR PRIVADO | F84: SI | G84: NO | H84: SI | I84: 34 | J84: =IF(1.96<ABS(C84-$S$23)/$S$24,"Atípico","No") -> No | K84: =IF(1.96<ABS((I84-$T$23)/$T$24),"Atípico", "No") -> No | L84: =IF(ISBLANK(C84),$S$23,C84) -> 415861 | M84: =IF(ISBLANK(D84),_xlfn.MODE.SNGL(moras[TIPO_ASEGURAMIENTO]),D84) -> TRABAJADOR INDEPENDIENTE | N84: =IF(ISBLANK(moras[[#This Row],[EDAD]]),T105,moras[[#This Row],[EDAD]]) -> 34
A85: 84 | B85: MUJER | C85: 1404047 | D85: ASALARIADO | E85: SECTOR PUBLICO | F85: SI | G85: NO | H85: SI | I85: 53 | J85: =IF(1.96<ABS(C85-$S$23)/$S$24,"Atípico","No") -> No | K85: =IF(1.96<ABS((I85-$T$23)/$T$24),"Atípico", "No") -> No | L85: =IF(ISBLANK(C85),$S$23,C85) -> 1404047 | M85: =IF(ISBLANK(D85),_xlfn.MODE.SNGL(moras[TIPO_ASEGURAMIENTO]),D85) -> ASALARIADO | N85: =IF(ISBLANK(moras[[#This Row],[EDAD]]),T106,moras[[#This Row],[EDAD]]) -> 53
A86: 85 | B86: MUJER | C86: 457842.57 | D86: ASALARIADO | E86: SECTOR PRIVADO | F86: SI | G86: NO | H86: NO | I86: 50 | J86: =IF(1.96<ABS(C86-$S$23)/$S$24,"Atípico","No") -> No | K86: =IF(1.96<ABS((I86-$T$23)/$T$24),"Atípico", "No") -> No | L86: =IF(ISBLANK(C86),$S$23,C86) -> 457842.57 | M86: =IF(ISBLANK(D86),_xlfn.MODE.SNGL(moras[TIPO_ASEGURAMIENTO]),D86) -> ASALARIADO | N86: =IF(ISBLANK(moras[[#This Row],[EDAD]]),T107,moras[[#This Row],[EDAD]]) -> 50
A87: 86 | B87: MUJER | C87: 297046 | D87: ASEGURADO VOLUNTARIO | E87: SECTOR PRIVADO | F87: SI | G87: NO | H87: NO | I87: 36 | J87: =IF(1.96<ABS(C87-$S$23)/$S$24,"Atípico","No") -> No | K87: =IF(1.96<ABS((I87-$T$23)/$T$24),"Atípico", "No") -> No | L87: =IF(ISBLANK(C87),$S$23,C87) -> 297046 | M87: =IF(ISBLANK(D87),_xlfn.MODE.SNGL(moras[TIPO_ASEGURAMIENTO]),D87) -> ASEGURADO VOLUNTARIO | N87: =IF(ISBLANK(moras[[#This Row],[EDAD]]),T108,moras[[#This Row],[EDAD]]) -> 36
A88: 87 | B88: HOMBRE | C88: 347356.26 | D88: ASALARIADO | E88: SECTOR PRIVADO | F88: SI | G88: NO | H88: NO | I88: 38 | J88: =IF(1.96<ABS(C88-$S$23)/$S$24,"Atípico","No") -> No | K88: =IF(1.96<ABS((I88-$T$23)/$T$24),"Atípico", "No") -> No | L88: =IF(ISBLANK(C88),$S$23,C88) -> 347356.26 | M88: =IF(ISBLANK(D88),_xlfn.MODE.SNGL(moras[TIPO_ASEGURAMIENTO]),D88) -> ASALARIADO | N88: =IF(ISBLANK(moras[[#This Row],[EDAD]]),T109,moras[[#This Row],[EDAD]]) -> 38
A89: 88 | B89: MUJER | C89: 432031 | D89: ASALARIADO | E89: SECTOR PUBLICO | F89: SI | G89: NO | H89: SI | I89: 31 | J89: =IF(1.96<ABS(C89-$S$23)/$S$24,"Atípico","No") -> No | K89: =IF(1.96<ABS((I89-$T$23)/$T$24),"Atípico", "No") -> No | L89: =IF(ISBLANK(C89),$S$23,C89) -> 432031 | M89: =IF(ISBLANK(D89),_xlfn.MODE.SNGL(moras[TIPO_ASEGURAMIENTO]),D89) -> ASALARIADO | N89: =IF(ISBLANK(moras[[#This Row],[EDAD]]),T110,moras[[#This Row],[EDAD]]) -> 31
A90: 89 | B90: HOMBRE | C90: 419292 | D90: TRABAJADOR INDEPENDIENTE | E90: SECTOR PRIVADO | F90: SI | G90: SI | H90: NO | I90: 36 | J90: =IF(1.96<ABS(C90-$S$23)/$S$24,"Atípico","No") -> No | K90: =IF(1.96<ABS((I90-$T$23)/$T$24),"Atípico", "No") -> No | L90: =IF(ISBLANK(C90),$S$23,C90) -> 419292 | M90: =IF(ISBLANK(D90),_xlfn.MODE.SNGL(moras[TIPO_ASEGURAMIENTO]),D90) -> TRABAJADOR INDEPENDIENTE | N90: =IF(ISBLANK(moras[[#This Row],[EDAD]]),T111,moras[[#This Row],[EDAD]]) -> 36
A91: 90 | B91: MUJER | C91: 622035.82 | D91: ASALARIADO | E91: SECTOR PUBLICO | F91: SI | G91: NO | H91: NO | I91: 30 | J91: =IF(1.96<ABS(C91-$S$23)/$S$24,"Atípico","No") -> No | K91: =IF(1.96<ABS((I91-$T$23)/$T$24),"Atípico", "No") -> No | L91: =IF(ISBLANK(C91),$S$23,C91) -> 622035.82 | M91: =IF(ISBLANK(D91),_xlfn.MODE.SNGL(moras[TIPO_ASEGURAMIENTO]),D91) -> ASALARIADO | N91: =IF(ISBLANK(moras[[#This Row],[EDAD]]),T112,moras[[#This Row],[EDAD]]) -> 30
A92: 91 | B92: HOMBRE | C92: 483142.5 | D92: ASALARIADO | E92: SECTOR PRIVADO | F92: SI | G92: NO | H92: NO | I92: 33 | J92: =IF(1.96<ABS(C92-$S$23)/$S$24,"Atípico","No") -> No | K92: =IF(1.96<ABS((I92-$T$23)/$T$24),"Atípico", "No") -> No | L92: =IF(ISBLANK(C92),$S$23,C92) -> 483142.5 | M92: =IF(ISBLANK(D92),_xlfn.MODE.SNGL(moras[TIPO_ASEGURAMIENTO]),D92) -> ASALARIADO | N92: =IF(ISBLANK(moras[[#This Row],[EDAD]]),T113,moras[[#This Row],[EDAD]]) -> 33
... A103: 102 | B103: MUJER | C103: 377900 | D103: ASALARIADO | E103: SECTOR PRIVADO | F103: SI | G103: NO | H103: NO | I103: 57 | J103: =IF(1.96<ABS(C103-$S$23)/$S$24,"Atípico","No") -> No | K103: =IF(1.96<ABS((I103-$T$23)/$T$24),"Atípico", "No") -> No | L103: =IF(ISBLANK(C103),$S$23,C103) -> 377900 | M103: =IF(ISBLANK(D103),_xlfn.MODE.SNGL(moras[TIPO_ASEGURAMIENTO]),D103) -> ASALARIADO | N103: =IF(ISBLANK(moras[[#This Row],[EDAD]]),T124,moras[[#This Row],[EDAD]]) -> 57
A104: 103 | B104: HOMBRE | C104: 300018 | D104: ASEGURADO VOLUNTARIO | E104: SECTOR PRIVADO | F104: SI | G104: NO | H104: NO | I104: 63 | J104: =IF(1.96<ABS(C104-$S$23)/$S$24,"Atípico","No") -> No | K104: =IF(1.96<ABS((I104-$T$23)/$T$24),"Atípico", "No") -> No | L104: =IF(ISBLANK(C104),$S$23,C104) -> 300018 | M104: =IF(ISBLANK(D104),_xlfn.MODE.SNGL(moras[TIPO_ASEGURAMIENTO]),D104) -> ASEGURADO VOLUNTARIO | N104: =IF(ISBLANK(moras[[#This Row],[EDAD]]),T125,moras[[#This Row],[EDAD]]) -> 63 | AB104: Este gráfico nos indica que hay pocos extranjeros que están haciendo un trámite lo cual tiene sentido para una empresa nacional que no está en busca de un mercado en el extranjero.
A105: 104 | B105: MUJER | C105: 306643.32 | D105: ASALARIADO | E105: SECTOR PRIVADO | F105: SI | G105: NO | H105: NO | I105: 30 | J105: =IF(1.96<ABS(C105-$S$23)/$S$24,"Atípico","No") -> No | K105: =IF(1.96<ABS((I105-$T$23)/$T$24),"Atípico", "No") -> No | L105: =IF(ISBLANK(C105),$S$23,C105) -> 306643.32 | M105: =IF(ISBLANK(D105),_xlfn.MODE.SNGL(moras[TIPO_ASEGURAMIENTO]),D105) -> ASALARIADO | N105: =IF(ISBLANK(moras[[#This Row],[EDAD]]),T126,moras[[#This Row],[EDAD]]) -> 30
A106: 105 | B106: HOMBRE | C106: 462759 | D106: ASALARIADO | E106: SECTOR PRIVADO | F106: SI | G106: NO | H106: NO | I106: 35 | J106: =IF(1.96<ABS(C106-$S$23)/$S$24,"Atípico","No") -> No | K106: =IF(1.96<ABS((I106-$T$23)/$T$24),"Atípico", "No") -> No | L106: =IF(ISBLANK(C106),$S$23,C106) -> 462759 | M106: =IF(ISBLANK(D106),_xlfn.MODE.SNGL(moras[TIPO_ASEGURAMIENTO]),D106) -> ASALARIADO | N106: =IF(ISBLANK(moras[[#This Row],[EDAD]]),T127,moras[[#This Row],[EDAD]]) -> 35
A107: 106 | B107: MUJER | C107: 1411236 | D107: ASALARIADO | E107: SECTOR PUBLICO | F107: SI | G107: NO | H107: NO | I107: 30 | J107: =IF(1.96<ABS(C107-$S$23)/$S$24,"Atípico","No") -> No | K107: =IF(1.96<ABS((I107-$T$23)/$T$24),"Atípico", "No") -> No | L107: =IF(ISBLANK(C107),$S$23,C107) -> 1411236 | M107: =IF(ISBLANK(D107),_xlfn.MODE.SNGL(moras[TIPO_ASEGURAMIENTO]),D107) -> ASALARIADO | N107: =IF(ISBLANK(moras[[#This Row],[EDAD]]),T128,moras[[#This Row],[EDAD]]) -> 30 | U107: En esta data las personas que no están activas son ínfimas y los activos son casi casi la mayoría entonces los datos de morosidad están actualizados pero están cesgados por la censura estadística.
A108: 107 | B108: HOMBRE | C108: 310124 | D108: ASEGURADO VOLUNTARIO | E108: SECTOR PRIVADO | F108: SI | G108: NO | H108: NO | I108: 51 | J108: =IF(1.96<ABS(C108-$S$23)/$S$24,"Atípico","No") -> No | K108: =IF(1.96<ABS((I108-$T$23)/$T$24),"Atípico", "No") -> No | L108: =IF(ISBLANK(C108),$S$23,C108) -> 310124 | M108: =IF(ISBLANK(D108),_xlfn.MODE.SNGL(moras[TIPO_ASEGURAMIENTO]),D108) -> ASEGURADO VOLUNTARIO | N108: =IF(ISBLANK(moras[[#This Row],[EDAD]]),T129,moras[[#This Row],[EDAD]]) -> 51
A109: 108 | B109: HOMBRE | C109: 505145 | D109: TRABAJADOR INDEPENDIENTE | E109: SECTOR PRIVADO | F109: SI | G109: SI | H109: SI | I109: 30 | J109: =IF(1.96<ABS(C109-$S$23)/$S$24,"Atípico","No") -> No | K109: =IF(1.96<ABS((I109-$T$23)/$T$24),"Atípico", "No") -> No | L109: =IF(ISBLANK(C109),$S$23,C109) -> 505145 | M109: =IF(ISBLANK(D109),_xlfn.MODE.SNGL(moras[TIPO_ASEGURAMIENTO]),D109) -> TRABAJADOR INDEPENDIENTE | N109: =IF(ISBLANK(moras[[#This Row],[EDAD]]),T130,moras[[#This Row],[EDAD]]) -> 30
A110: 109 | B110: HOMBRE | C110: 386161 | D110: TRABAJADOR INDEPENDIENTE | E110: SECTOR PRIVADO | F110: SI | G110: NO | H110: SI | I110: 44 | J110: =IF(1.96<ABS(C110-$S$23)/$S$24,"Atípico","No") -> No | K110: =IF(1.96<ABS((I110-$T$23)/$T$24),"Atípico", "No") -> No | L110: =IF(ISBLANK(C110),$S$23,C110) -> 386161 | M110: =IF(ISBLANK(D110),_xlfn.MODE.SNGL(moras[TIPO_ASEGURAMIENTO]),D110) -> TRABAJADOR INDEPENDIENTE | N110: =IF(ISBLANK(moras[[#This Row],[EDAD]]),T131,moras[[#This Row],[EDAD]]) -> 44
...

Sheet Hoja3
A3: SEXO | B3: Cuenta de SEXO
A4: HOMBRE | B4: 3012
A5: MUJER | B5: 1988

Sheet Hoja4
A3: TIPO_ASEGURADO_IMPUTADO | B3: Cuenta de TIPO_ASEGURADO_IMPUTADO
A4: ASALARIADO | B4: 3464
A5: ASEGURADO VOLUNTARIO | B5: 436
A6: CONVENIOS ESPECIALES DE ASEGURADOS VOLUNTARIOS | B6: 31
A7: CONVENIOS ESPECIALES DE TRABAJADORES INDEPENDIENTES | B7: 157
A8: PENSIONADOS EN SU PROPIO SISTEMA | B8: 212
A9: TRABAJADOR INDEPENDIENTE | B9: 700

Sheet Hoja5
A3: SECTOR | B3: Cuenta de SECTOR
A4: SECTOR PRIVADO | B4: 3906
A5: SECTOR PUBLICO | B5: 1094

Sheet Hoja6
A3: INDICADOR_ACTIVO | B3: Cuenta de INDICADOR_ACTIVO
A4: NO | B4: 34
A5: SI | B5: 4966

Sheet Hoja7
A3: INDICADOR.EXTRANJERO | B3: Cuenta de INDICADOR.EXTRANJERO
A4: NO | B4: 4397
A5: SI | B5: 603

Sheet Hoja8
A3: INDICADOR_MOROSO | B3: Cuenta de INDICADOR_MOROSO
A4: NO | B4: 4130
A5: SI | B5: 870

Sheet Hoja9
A3: Z-SCORE_SALARIO | B3: Cuenta de Z-SCORE_SALARIO
A4: Atípico | B4: 162
A5: No | B5: 4838
